{
  "schema_version": "atlas.release_provenance.v1",
  "generated": "2026-04-28T00:12:55Z",
  "metadata_only": true,
  "commit": "dc021f5be09408fe0913511e1f099a46df1b2883",
  "signed_tag": {
    "name": "atlas-production-candidate-m78",
    "target": "dc021f5be09408fe0913511e1f099a46df1b2883",
    "tag_object": "9f8e9dbc43b8844098507b02af1f58dd7e763738",
    "verification": "verified",
    "signer_fingerprint": "24B1E00EEB286B966F9FCE0C9C6439E15BBFD290",
    "public_key_path": "docs/retention/releases/atlas-m67-release-signing-public-key.asc",
    "public_key_sha256": "c08e7454ee3ab72a39286f61efd4deca8fbe0ef3fe20844771ff5735da6a79d5"
  },
  "release_packet": {
    "path": "docs/retention/releases/atlas-m78-business-flow-readiness.json",
    "sha256": "474f6b6182cd80054af52a36ef021bd7d03c96a0cdb7b457cde08ce1277deee6"
  },
  "qa": {
    "status": "pass",
    "command": "nix-shell --run './bin/dev-qa'",
    "note": "dev-qa passed with 91/91 tests, lint ok, and stress ok before M78 business-flow readiness release packet"
  },
  "production_status": {
    "observed": "not-ready",
    "note": "provenance and dry-run evidence were pending before retaining this packet set"
  },
  "known_limitations": [
    "local signed-tag provenance is not an external audit",
    "release packet files are hash-bound by provenance but are not individually signed",
    "Business Flow Evidence remains optional and non-blocking in v1 and production readiness",
    "Business Flow Evidence JSON parity, finding links, validation links, retention links, and required-pillar promotion remain planned",
    "Atlas production status is a local contract, not deployment certification"
  ],
  "no_production_overclaim": true
}
